gigapipe/__init__.py
gigapipe/main.py
gigapipe/api_client/__init__.py
gigapipe/api_client/gigapipe_api.py
gigapipe/api_client/gigapipe_client.py
gigapipe/api_client/api/__init__.py
gigapipe/api_client/api/backups.py
gigapipe/api_client/api/base.py
gigapipe/api_client/api/clickhouse.py
gigapipe/api_client/api/clusters.py
gigapipe/api_client/api/imports.py
gigapipe/api_client/api/integrations.py
gigapipe/api_client/api/invites.py
gigapipe/api_client/api/organizations.py
gigapipe/api_client/api/roles.py
gigapipe/api_client/api/root.py
gigapipe/api_client/api/stripe.py
gigapipe/api_client/api/users.py
gigapipe/exceptions/__init__.py
gigapipe/exceptions/exceptions.py
gigapipe/exceptions/gigapipe_error.py
gigapipe/gigapipe_api_client/__init__.py
gigapipe/gigapipe_api_client/gigapipe_api.py
gigapipe/gigapipe_api_client/gigapipe_client.py
gigapipe/gigapipe_api_client/api/__init__.py
gigapipe/gigapipe_api_client/api/base.py
gigapipe/gigapipe_api_client/api/invites.py
gigapipe/gigapipe_api_client/api/organizations.py
gigapipe/gigapipe_api_client/api/roles.py
gigapipe/gigapipe_api_client/api/users.py
gigapipe-0.1.22.dist-info/LICENSE
gigapipe-0.1.22.dist-info/LICENSE.txt
gigapipe-0.1.22.dist-info/METADATA
gigapipe-0.1.22.dist-info/WHEEL
gigapipe-0.1.22.dist-info/top_level.txt
gigapipe-0.1.22.dist-info/RECORD
