Metadata-Version: 2.1
Name: gigapipe
Version: 0.1.22
Summary: Gigapipe Python Client
Home-page: https://www.gigapipe.com
Author: Gigapipe
Author-email: info@gigapipe.com
License: MIT
Project-URL: Github, https://github.com/gigapipehq/gigapipe-python-client
Keywords: bigdata,gigapipe,clickhouse
Platform: UNKNOWN
Classifier: Development Status :: 5 - Production/Stable
Classifier: Intended Audience :: Developers
Classifier: Operating System :: Unix
Classifier: Operating System :: MacOS :: MacOS X
Classifier: Operating System :: Microsoft :: Windows :: Windows 10
Classifier: License :: OSI Approved :: MIT License
Classifier: Programming Language :: Python :: 3
Requires-Dist: requests (==2.27.1)
